{"gZqD/y7KUeghTDwobfxSSw==":"durian_fruit_exotic_182295_2560x1600-2000x1250.jpg","gAE4wsjd1WAwAOOaa+96lA==":"preview.jpg","GnBJmEn1YoWtBQhSNKQAew==":"whatsapp%20image%202021-05-04%20at%2014.38.14%20(7)-696x464.jpeg","kWUth2gC7uHWYSdIG4LgUQ==":"whatsapp%20image%202021-05-04%20at%2014.38.14%20(8)-696x464.jpeg","OIAHQ2BP4bgAegsOi6iJ/w==":"whatsapp%20image%202021-05-04%20at%2014.38.14%20(8)-696x464.jpeg","BaAxIOd1qqhNTHcr43UpWA==":"whatsapp%20image%202021-05-04%20at%2014.40.32-696x691.jpeg","pYLAsDIcLwWQOMu6m5bXww==":"whatsapp%20image%202021-05-04%20at%2014.38.14%20(6)-696x464.jpeg","C0vJC6JxnzLgLnVPJCx7eg==":"06.jpg","ppaPdSqy52inTbLQF10RkQ==":"background5.jpg","vsO6wUy3eG3Utnf2qX87BA==":"whatsapp%20image%202021-05-04%20at%2014.38.14%20(1)-506x344.jpeg","xUcugJIxtGRuWVFBWUJB1Q==":"whatsapp%20image%202021-05-04%20at%2014.38.14%20(3)-506x337.jpeg","r3pi0sGVXhmKj7i5RP/wMA==":"whatsapp%20image%202021-05-04%20at%2014.38.14%20(4)-506x506.jpeg","Djmdwwl2W1S1J89RqmFJBQ==":"whatsapp%20image%202021-05-04%20at%2014.38.14%20(5)-506x507.jpeg","jlQ0Hx1KFnZFmsEUoTwwpg==":"icon-165x165.jpg","J408LjNeY/ChX3osLMBOOw==":"whatsapp%20image%202021-05-20%20at%2012.46.58-1170x1111.jpg","YUNe97A5/z7y6E/9vDoBkA==":"whatsapp%20image%202021-05-20%20at%2014.11.18-506x506.jpeg","OxTjyyQ3WL+quwX5+4oxfg==":"whatsapp%20image%202021-05-20%20at%2014.11.49-483x484.jpeg","xzeUh1QPdpKz4u8aLXV7iA==":"whatsapp%20image%202021-05-20%20at%2014.11.50-496x495.jpeg","2W7sbmm2hVMyVfzYrvMYhw==":"whatsapp%20image%202021-05-20%20at%2014.11.49%20(1)-696x870.jpg","OVYV2Ai/pYskSy0RmrnBig==":"whatsapp%20image%202021-05-20%20at%2014.11.49%20(1)-696x870.jpeg","9MASj6Fr+/3WgQPdM5NLbQ==":"whatsapp%20image%202021-05-20%20at%2014.11.48-427x485.jpeg","a5jklWE62N/jQSh/CtN5Sg==":"whatsapp%20image%202021-05-20%20at%2012.46.58-1170x1111.jpeg"}